sentraiq_core/__init__.py
sentraiq_core/config.py
sentraiq_core/moderator.py
sentraiq_core-0.0.2.dist-info/METADATA
sentraiq_core-0.0.2.dist-info/WHEEL
sentraiq_core-0.0.2.dist-info/top_level.txt
sentraiq_core-0.0.2.dist-info/RECORD
