Metadata-Version: 2.4
Name: sentraiq-core
Version: 0.0.2
Summary: A Python package for configurable content moderation.
Author-email: isaac <isaacinfrastructure@gmail.com>
Project-URL: Homepage, https://github.com/isaac-rnd/sentraiq-python-package
Project-URL: Bug Tracker, https://github.com/isaac-rnd/sentraiq-python-package/issues
Classifier: Programming Language :: Python :: 3
Classifier: License :: OSI Approved :: MIT License
Classifier: Operating System :: OS Independent
Requires-Python: >=3.8
